{
  "project_name": "ItunesExample",
  "spec_overrides": {},
  "skip_licenses": [],
  "skip_pods": [],
  "force_prebuild_pods": [],
  "build_settings": {
    "ENABLE_BITCODE": "YES",
    "GCC_OPTIMIZATION_LEVEL": "s",
    "SWIFT_OPTIMIZATION_LEVEL": "-Osize",
    "SWIFT_COMPILATION_MODE": "wholemodule",
    "CODE_SIGN_IDENTITY": "",
    "CODE_SIGNING_REQUIRED": "NO",
    "CODE_SIGN_ENTITLEMENTS": "",
    "CODE_SIGNING_ALLOWED": "NO",
    "OTHER_SWIFT_FLAGS": "-Xfrontend -module-interface-preserve-types-as-written"
  },
  "build_settings_overrides": {},
  "build_system": "Latest",
  "build_xcframeworks_all": true,
  "library_evolution_support": true,
  "license_filename": "Pods-acknowledgements",
  "restore_enabled": true,
  "allow_building_development_pods": false,
  "use_bundler": false,
  "deterministic_build": false,
  "build_using_repo_paths": false,
  "react_native_project": false,
  "development_team": ""
}